{
  "book": "Language Hub",
  "CEFRLevel": "B1_plus",
  "dialect": "American",
  "chapters": [
    {
      "chapterUnit": 9,
      "chapterTitle": "The arts ",
      "chapterQuote": "Art is unquestionably one of the purest and highest elements in human happiness. John Lubbock",
      "chapterFrontImage": "",
      "chapterObjectives": [
        "suggest improvements to a proposal",
        "plan an arts event",
        "report a conversation",
        "create a collaborative story",
        "talk about movies and books",
        "write a review"
      ],
      "sections": [
        {
          "sectionNumber": 9.1,
          "sectionTitle": "Art for everybody",
          "sectionObjectives": [
            "Suggest improvements to a proposal",
            "Plan an arts event"
          ],
          "GKU": "Language_Hub_B1plus_Unit9_Lesson9_1",
          "sectionSkills": [
            {
              "skillType": "V",
              "skillName": "Vocabulary",
              "skillTitle": "the arts; verbal idioms"
            },
            {
              "skillType": "G",
              "skillName": "Grammar",
              "skillTitle": "second conditional"
            },
            {
              "skillType": "P",
              "skillName": "Pronunciation",
              "skillTitle": "/ʧ/, /ʃ/ and /k/"
            },
            {
              "skillType": "S",
              "skillName": "Reading",
              "skillTitle": "using linking words to understand the writer’s opinion"
            }
          ],
          "sectionPart": [
            {
              "partTitle": "GRAMMAR",
              "partImage": "",
              "partSubTitle": "Second conditional",
              "textMode": "full article",
              "textContents": [
                {
                  "paragraphOrdinal": 1,
                  "paragraphTitle": "Second conditional",
                  "paragraphSubtitles": [
                    "Sentences from the council meeting"
                  ],
                  "paragraphContents": [
                    "Look at the sentences from the council meeting and answer the questions that follow."
                  ]
                },
                {
                  "paragraphOrdinal": 2,
                  "paragraphTitle": null,
                  "paragraphSubtitles": [
                    "a"
                  ],
                  "paragraphContents": [
                    "If we open a community music center, it will change thousands of people’s lives."
                  ]
                },
                {
                  "paragraphOrdinal": 3,
                  "paragraphTitle": null,
                  "paragraphSubtitles": [
                    "b"
                  ],
                  "paragraphContents": [
                    "If we turned the warehouse into a theater, it would make a lot of money."
                  ]
                },
                {
                  "paragraphOrdinal": 4,
                  "paragraphTitle": null,
                  "paragraphSubtitles": [
                    "c"
                  ],
                  "paragraphContents": [
                    "If we had a good, modern theater in this city, it would be extremely popular."
                  ]
                },
                {
                  "paragraphOrdinal": 5,
                  "paragraphTitle": null,
                  "paragraphSubtitles": [
                    "d"
                  ],
                  "paragraphContents": [
                    "If the city council had three warehouses, maybe we could do all of those wonderful things."
                  ]
                }
              ],
              "sets": [
                {
                  "setMarker": "A",
                  "setHeading": "WORK IT OUT",
                  "textImage": null,
                  "setAudioNumber": null,
                  "setIgnore": false,
                  "exerciseType": "RC - multiple choice",
                  "exerciseInstruction": "Look at the sentences from the council meeting and answer the questions that follow.",
                  "exercises": [
                    {
                      "sentenceOrdinal": 1,
                      "paragraphOrdinal": null,
                      "exerciseQuestion": "Sentences a and b are both about the future. Which speaker is more certain that their plans will really happen?",
                      "exerciseMinAnswer": null,
                      "exerciseMaxAnswer": null,
                      "exerciseAnswers": "a",
                      "LKUs": [],
                      "sentenceAnswerOptions": [
                        "a",
                        "b"
                      ],
                      "context": "textContents"
                    },
                    {
                      "sentenceOrdinal": 2,
                      "paragraphOrdinal": null,
                      "exerciseQuestion": "In sentence c, does the city have a theater right now?",
                      "exerciseMinAnswer": null,
                      "exerciseMaxAnswer": null,
                      "exerciseAnswers": "no",
                      "LKUs": [],
                      "sentenceAnswerOptions": [
                        "yes",
                        "no"
                      ],
                      "context": "textContents"
                    },
                    {
                      "sentenceOrdinal": 3,
                      "paragraphOrdinal": null,
                      "exerciseQuestion": "In sentence d, does the city council have three warehouses? Can they do all three things?",
                      "exerciseMinAnswer": null,
                      "exerciseMaxAnswer": null,
                      "exerciseAnswers": "no",
                      "LKUs": [],
                      "sentenceAnswerOptions": [
                        "yes",
                        "no"
                      ],
                      "context": "textContents"
                    }
                  ]
                }
              ]
            },
            {
              "partTitle": "GRAMMAR",
              "partImage": "",
              "partSubTitle": "Second conditional",
              "textMode": "full article",
              "textContents": [
                {
                  "paragraphOrdinal": 1,
                  "paragraphTitle": "Second conditional",
                  "paragraphSubtitles": [],
                  "paragraphContents": [
                    "Complete the rules with the correct words."
                  ]
                },
                {
                  "paragraphOrdinal": 2,
                  "paragraphTitle": null,
                  "paragraphSubtitles": [],
                  "paragraphContents": [
                    "Conditional sentences usually have two clauses: the if clause and the result clause. To make second conditional sentences, we use If + simple past and would + base form of the verb."
                  ]
                },
                {
                  "paragraphOrdinal": 3,
                  "paragraphTitle": null,
                  "paragraphSubtitles": [],
                  "paragraphContents": [
                    "With the verb be, we use 'were' instead of 'was'.",
                    "If I were you, I’d vote for the first proposal."
                  ]
                },
                {
                  "paragraphOrdinal": 4,
                  "paragraphTitle": null,
                  "paragraphSubtitles": [],
                  "paragraphContents": [
                    "We use the second conditional to talk about unreal or impossible situations in the present or future."
                  ]
                },
                {
                  "paragraphOrdinal": 5,
                  "paragraphTitle": null,
                  "paragraphSubtitles": [],
                  "paragraphContents": [
                    "If we are not sure of the result, we can use might or could instead of would in the result clause."
                  ]
                }
              ],
              "sets": [
                {
                  "setMarker": "B",
                  "setHeading": "",
                  "setImage": "",
                  "setAudioNumber": null,
                  "setIgnore": false,
                  "exerciseType": "RC - word bank",
                  "exerciseInstruction": "Complete the rules with the correct words.",
                  "exercises": [
                    {
                      "sentenceOrdinal": 1,
                      "paragraphOrdinal": 1,
                      "exerciseQuestion": null,
                      "exerciseMaxAnswer": null,
                      "exerciseMinAnswer": null,
                      "sentenceAnswerOptions": [
                        "could",
                        "base",
                        "past",
                        "unreal",
                        "were"
                      ],
                      "LKUs": [],
                      "context": "textContents"
                    }
                  ]
                }
              ]
            },
            {
              "partTitle": "GRAMMAR",
              "partImage": "",
              "partSubTitle": "Second conditional",
              "sets": [
                {
                  "setMarker": "C",
                  "setHeading": "",
                  "setImage": "",
                  "setAudioNumber": null,
                  "setIgnore": true,
                  "exerciseType": "",
                  "exerciseInstruction": "Go to the Grammar Hub on page 138.",
                  "exercises": null
                }
              ]
            },
            {
              "partTitle": "GRAMMAR",
              "partImage": "",
              "partSubTitle": "Second conditional",
              "sets": [
                {
                  "setMarker": "D",
                  "setHeading": "SPEAK",
                  "setImage": "",
                  "setAudioNumber": null,
                  "setIgnore": true,
                  "exerciseType": "",
                  "exerciseInstruction": "Work in pairs and discuss the questions.",
                  "exercises": null
                }
              ]
            },
            {
              "partTitle": "GRAMMAR",
              "partImage": "",
              "partSubTitle": "Second conditional",
              "sets": [
                {
                  "setMarker": "A",
                  "setHeading": "",
                  "setImage": "",
                  "setAudioNumber": null,
                  "setIgnore": false,
                  "exerciseType": "one page sequence - multiple choice",
                  "exerciseInstruction": "Choose the correct option.",
                  "exercises": [
                    {
                      "exerciseSentences": [
                        {
                          "sentenceOrdinal": 1,
                          "sentences": [
                            "If I knew / know the words to the song, I would sing it."
                          ],
                          "exerciseAnswers": "knew",
                          "exerciseOptions": [
                            "knew",
                            "know"
                          ]
                        },
                        {
                          "sentenceOrdinal": 2,
                          "sentences": [
                            "If she had a better idea for the story, she uses / would use it."
                          ],
                          "exerciseAnswers": "would use",
                          "exerciseOptions": [
                            "uses",
                            "would use"
                          ]
                        },
                        {
                          "sentenceOrdinal": 3,
                          "sentences": [
                            "If we would hold / held an art competition, many people would take part."
                          ],
                          "exerciseAnswers": "held",
                          "exerciseOptions": [
                            "would hold",
                            "held"
                          ]
                        },
                        {
                          "sentenceOrdinal": 4,
                          "sentences": [
                            "The public liked / might like his proposal if he presented it to them."
                          ],
                          "exerciseAnswers": "might like",
                          "exerciseOptions": [
                            "liked",
                            "might like"
                          ]
                        },
                        {
                          "sentenceOrdinal": 5,
                          "sentences": [
                            "If you invite / invited Monique to the play, would she come?"
                          ],
                          "exerciseAnswers": "invited",
                          "exerciseOptions": [
                            "invite",
                            "invited"
                          ]
                        },
                        {
                          "sentenceOrdinal": 6,
                          "sentences": [
                            "If they allowed the public behind the stage, the actors weren’t / wouldn’t be pleased."
                          ],
                          "exerciseAnswers": "wouldn't be",
                          "exerciseOptions": [
                            "weren't",
                            "wouldn't be "
                          ]
                        },
                        {
                          "sentenceOrdinal": 7,
                          "sentences": [
                            "I’d study art at Kingston University if I were / am you."
                          ],
                          "exerciseAnswers": "were",
                          "exerciseOptions": [
                            "were",
                            "am "
                          ]
                        }
                      ]
                    }
                  ]
                }
              ]
            }
          ]
        },
        {
          "sectionNumber": 9.2,
          "sectionTitle": "Tell me a story",
          "sectionObjectives": [
            "Report a conversation",
            "Create a collaborative story"
          ],
          "GKU": "Language_Hub_B1plus_Unit9_Lesson9_2",
          "sectionSkills": [
            {
              "skillType": "G",
              "skillName": "Grammar",
              "skillTitle": "reported speech"
            },
            {
              "skillType": "V",
              "skillName": "Vocabulary",
              "skillTitle": "reporting verbs"
            },
            {
              "skillType": "P",
              "skillName": "Pronunciation",
              "skillTitle": "using your voice to make a story more interesting"
            },
            {
              "skillType": "S",
              "skillName": "Listening",
              "skillTitle": "listening for definitions of new words"
            }
          ],
          "sectionPart": [
            {
              "partTitle": "GRAMMAR",
              "partImage": "",
              "partSubTitle": "Reported Speech",
              "textMode": "full article",
              "textContents": [
                {
                  "paragraphOrdinal": 1,
                  "paragraphTitle": "CHAPTER 3: I MEET GATSBY",
                  "paragraphSubtitles": [
                    "PART 2"
                  ],
                  "paragraphContents": [
                    "Supper was now being served. Jordan and I left our table and went to look for Gatsby. People were dancing now. The voices and the laughter were very loud. The moon was high in the sky. Jordan and I sat down at a table with a well-dressed man of my own age. I was enjoying myself, now. The music stopped for a moment. The man at our table looked at me and smiled. ‘I think I know your face,’ the man said. ‘Weren’t you in France during the War?’",
                    "‘Yes, I was.’",
                    "‘Me, too,’ he said. We talked about the War for a few minutes. Then the man told me that he had a new motorboat."
                  ]
                }
              ],
              "sets": [
                {
                  "setMarker": "A",
                  "setHeading": "WORK IT OUT",
                  "textImage": "",
                  "setAudioNumber": null,
                  "setIgnore": false,
                  "exerciseType": "RC - multiple choice",
                  "exerciseInstruction": "Read the text from 'The Great Gatsby', Chapter 3, Part 2 then answer the following question.",
                  "exercises": [
                    {
                      "sentenceOrdinal": 1,
                      "paragraphOrdinal": null,
                      "exerciseQuestion": "Look at the phrase 'he had a new motorboat'. How would you rewrite it in direct speech to show what Gatsby actually said?",
                      "exerciseMinAnswer": null,
                      "exerciseMaxAnswer": null,
                      "exerciseAnswers": "I have a new motorboat.",
                      "LKUs": [],
                      "sentenceAnswerOptions": [
                        "I had a new motorboat",
                        "I have a new motoboat"
                      ],
                      "context": "textContents"
                    }
                  ]
                }
              ]
            },
            {
              "partTitle": "GRAMMAR",
              "partImage": "",
              "partSubTitle": "Reported speech",
              "textMode": "full article",
              "textContents": [
                {
                  "paragraphOrdinal": 1,
                  "paragraphTitle": "Reported speech",
                  "paragraphSubtitles": [],
                  "paragraphContents": [
                    "Complete the examples in the correct tense."
                  ]
                },
                {
                  "paragraphOrdinal": 2,
                  "paragraphTitle": "Direct speech / Reported speech",
                  "paragraphSubtitles": [
                    "Simple present (direct speech) / Simple past (reported speech)"
                  ],
                  "paragraphContents": [
                    "‘My name’s Jay Gatsby.’ / He told me his name was Jay Gatsby"
                  ]
                },
                {
                  "paragraphOrdinal": 3,
                  "paragraphTitle": null,
                  "paragraphSubtitles": [
                    "Present progressive (direct speech) / Past progressive (reported speech)"
                  ],
                  "paragraphContents": [
                    "‘I’m really enjoying the party.’ / I told him I was really enjoying the party."
                  ]
                },
                {
                  "paragraphOrdinal": 4,
                  "paragraphTitle": null,
                  "paragraphSubtitles": [
                    "Present perfect (direct speech) / Past perfect (reported speech)"
                  ],
                  "paragraphContents": [
                    "‘I’ve never met Gatsby.’ / He said he had never met Gatsby."
                  ]
                },
                {
                  "paragraphOrdinal": 5,
                  "paragraphTitle": null,
                  "paragraphSubtitles": [
                    "Simple past (direct speech) / Past perfect (reported speech)"
                  ],
                  "paragraphContents": [
                    "‘Gatsby sent me a new dress.’ / She said Gatsby had sent her a new dress."
                  ]
                },
                {
                  "paragraphOrdinal": 6,
                  "paragraphTitle": null,
                  "paragraphSubtitles": [
                    "can (direct speech) / could (reported speech)"
                  ],
                  "paragraphContents": [
                    "‘I can’t see the host.’ / I told him I couldn't see the host."
                  ]
                },
                {
                  "paragraphOrdinal": 7,
                  "paragraphTitle": null,
                  "paragraphSubtitles": [
                    "will (direct speech) / would (reported speech)"
                  ],
                  "paragraphContents": [
                    "‘We’ll have a great time on my boat.’ / He said we would have a great time on his boat."
                  ]
                }
              ],
              "sets": [
                {
                  "setMarker": "B",
                  "setHeading": "",
                  "setImage": "",
                  "setAudioNumber": null,
                  "setIgnore": false,
                  "exerciseType": "RC - word bank",
                  "exerciseInstruction": "Complete the examples in the correct tense.",
                  "exercises": [
                    {
                      "sentenceOrdinal": 1,
                      "paragraphOrdinal": 1,
                      "exerciseQuestion": null,
                      "exerciseMaxAnswer": null,
                      "exerciseMinAnswer": null,
                      "sentenceAnswerOptions": [
                        "was",
                        "was",
                        "had",
                        "had",
                        "couldn't",
                        "would"
                      ],
                      "LKUs": [],
                      "context": "textContents"
                    }
                  ]
                }
              ]
            },
            {
              "partTitle": "GRAMMAR",
              "partImage": "",
              "partSubTitle": "Reported speech",
              "sets": [
                {
                  "setMarker": "C",
                  "setHeading": "",
                  "setImage": "",
                  "setAudioNumber": null,
                  "setIgnore": true,
                  "exerciseType": "",
                  "exerciseInstruction": "Go to the Grammar Hub on page 138.",
                  "exercises": null
                }
              ]
            },
            {
              "partTitle": "GRAMMAR",
              "partImage": "",
              "partSubTitle": "Reported speech",
              "sets": [
                {
                  "setMarker": "D",
                  "setHeading": "",
                  "setImage": "",
                  "setAudioNumber": null,
                  "setIgnore": false,
                  "exerciseType": "Rewrite",
                  "exerciseInstruction": "Report the sentences from The Great Gatsby.",
                  "exercises": [
                    {
                      "sentenceOrdinal": 1,
                      "sentences": [
                        "‘Do you come to these parties often?’ Jordan asked her."
                      ],
                      "blankedWords": [],
                      "exerciseAnswers": "Jordan asked the girl if she came to these parties often."
                    },
                    {
                      "sentenceOrdinal": 2,
                      "sentences": [
                        "I come when I can,’ the girl said."
                      ],
                      "blankedWords": [],
                      "exerciseAnswers": "The girl said said she came when she could."
                    },
                    {
                      "sentenceOrdinal": 3,
                      "sentences": [
                        "‘I think I know your face,’ the man said."
                      ],
                      "blankedWords": [],
                      "exerciseAnswers": "The man said he thought he knew his face. "
                    },
                    {
                      "sentenceOrdinal": 4,
                      "sentences": [
                        "‘This is an unusual party,’ I told the man. ‘I haven’t seen my host yet.’"
                      ],
                      "blankedWords": [],
                      "exerciseAnswers": "He told the man that it was an unusual party. He said he hadn't seen his host yet."
                    },
                    {
                      "sentenceOrdinal": 5,
                      "sentences": [
                        "‘Gatsby sent me an invitation this morning.’"
                      ],
                      "blankedWords": [],
                      "exerciseAnswers": "He said that Gatsby had sent him an invitation that morning."
                    }
                  ]
                }
              ]
            },
            {
              "partTitle": "GRAMMAR",
              "partImage": "",
              "partSubTitle": "Reported speech",
              "sets": [
                {
                  "setMarker": "E",
                  "setHeading": "SPEAK",
                  "setImage": "",
                  "setAudioNumber": null,
                  "setIgnore": true,
                  "exerciseType": "",
                  "exerciseInstruction": "Work in pairs. Use your imagination to tell the next part of the story. Report the conversation between Jay and Nick the next morning.",
                  "exercises": null
                }
              ]
            }
          ]
        }
      ]
    }
  ]
}