{
  "book": "Language Hub",
  "CEFRLevel": "B1_plus",
  "dialect": "American",
  "chapters": [
    {
      "chapterUnit": 2,
      "chapterTitle": "Experiences",
      "chapterQuote": "Nothing is a waste of time if you use the experience wisely. Auguste Rodin",
      "chapterFrontImage": "",
      "chapterObjectives": [
        "talk about past experiences and things you want to do",
        "talk about a life-changing decision",
        "talk about an inspirational person",
        "talk about solving a problem",
        "ask for, give and refuse permission",
        "write an informal email"
      ],
      "sections": [
        {
          "sectionNumber": 2.1,
          "sectionTitle": "Important decisions",
          "sectionObjectives": [
            "Talk about past experiences and things you want to do",
            "Talk about a life-changing decision"
          ],
          "GKU": "Language_Hub_B1plus_Unit2_Lesson2_1",
          "sectionSkills": [
            {
              "skillType": "G",
              "skillName": "Grammar",
              "skillTitle": "present perfect and simple past"
            },
            {
              "skillType": "P",
              "skillName": "Pronunciation",
              "skillTitle": "’s and ’ve"
            },
            {
              "skillType": "V",
              "skillName": "Vocabulary",
              "skillTitle": "collocations: making big decisions"
            },
            {
              "skillType": "S",
              "skillName": "Listening",
              "skillTitle": "listening for the main idea"
            }
          ],
          "sectionPart": [
            {
              "partTitle": "PRONUNCIATION",
              "partImage": "",
              "partSubTitle": "'s and 've",
              "sets": [
                {
                  "setMarker": "A",
                  "setHeading": "",
                  "setImage": "",
                  "setAudioNumber": 2.1,
                  "audioNumberOrdinal": "001",
                  "setAudio": "ALH_TAT3_AUD_U2.1_001",
                  "setIgnore": false,
                  "exerciseType": "LC - multiple choice",
                  "exerciseInstruction": "Listen to the pairs of sentences (1–6). Which sentence (a or b) is in the present perfect?",
                  "exercises": [
                    {
                      "exerciseSentences": [
                        {
                          "sentenceOrdinal": 1,
                          "sentences": [
                            "a. I made a declicious dinner. / I've made a delicious dinner."
                          ],
                          "exerciseAnswers": "b",
                          "exerciseOptions": [
                            "a",
                            "b"
                          ]
                        },
                        {
                          "sentenceOrdinal": 2,
                          "sentences": [
                            "a. You've painted a picture. / b. You painted a picture. "
                          ],
                          "exerciseAnswers": "a",
                          "exerciseOptions": [
                            "a",
                            "b"
                          ]
                        },
                        {
                          "sentenceOrdinal": 3,
                          "sentences": [
                            "a. She learned how to fly a plane. / b. She's learned how to fly a plane."
                          ],
                          "exerciseAnswers": "b",
                          "exerciseOptions": [
                            "a",
                            "b"
                          ]
                        },
                        {
                          "sentenceOrdinal": 4,
                          "sentences": [
                            "a. He bought a sports car. B. He's bought a sports car."
                          ],
                          "exerciseAnswers": "b",
                          "exerciseOptions": [
                            "a",
                            "b"
                          ]
                        },
                        {
                          "sentenceOrdinal": 5,
                          "sentences": [
                            "a. We've traveled around Asia. / b. We traveled around Asia."
                          ],
                          "exerciseAnswers": "a",
                          "exerciseOptions": [
                            "a",
                            "b"
                          ]
                        },
                        {
                          "sentenceOrdinal": 6,
                          "sentences": [
                            "a. They've planted a tree. / b. They planted a tree."
                          ],
                          "exerciseAnswers": "a",
                          "exerciseOptions": [
                            "a",
                            "b"
                          ]
                        }
                      ]
                    }
                  ]
                }
              ]
            }
          ]
        },
        {
          "sectionNumber": 2.2,
          "sectionTitle": "You can do it!",
          "sectionObjectives": [
            "Talk about an inspirational person",
            "Talk about solving a problem"
          ],
          "GKU": "Language_Hub_B1plus_Unit2_Lesson2_2",
          "sectionSkills": [
            {
              "skillType": "V",
              "skillName": "Vocabulary",
              "skillTitle": "dependent prepositions; problems and solutions"
            },
            {
              "skillType": "P",
              "skillName": "Pronunciation",
              "skillTitle": "word stress: verbs with two syllables"
            },
            {
              "skillType": "G",
              "skillName": "Grammar",
              "skillTitle": "present and past ability"
            },
            {
              "skillType": "S",
              "skillName": "Reading",
              "skillTitle": "deducing the meaning of unknown words from context"
            }
          ],
          "sectionPart": [
            {
              "partTitle": "PRONUNCIATION",
              "partImage": "",
              "partSubTitle": "Word stress: verbs with two syllables",
              "sets": [
                {
                  "setMarker": "A",
                  "setHeading": null,
                  "setImage": null,
                  "setAudioNumber": "",
                  "audioNumberOrdinal": "",
                  "setAudio": null,
                  "setIgnore": true,
                  "exerciseType": "",
                  "exerciseInstruction": "Work in pairs. Look at the verbs from the listening below. Take turns saying the verbs and marking the stress.",
                  "exercises": null
                }
              ]
            },
            {
              "partTitle": "PRONUNCIATION",
              "partImage": "",
              "partSubTitle": "Word stress: verbs with two syllables",
              "sets": [
                {
                  "setMarker": "B",
                  "setHeading": "",
                  "setImage": "",
                  "setAudioNumber": null,
                  "setIgnore": false,
                  "exerciseType": "one page sequence - multiple choice",
                  "exerciseInstruction": "Does the stress normally come on the first or second syllable?",
                  "exercises": [
                    {
                      "exerciseSentences": [
                        {
                          "sentenceOrdinal": 1,
                          "sentences": [
                            "Does the stress normally come on the first or second syllable?"
                          ],
                          "exerciseAnswers": "the second syllable",
                          "exerciseOptions": [
                            "the first syllable",
                            "the second syllable"
                          ]
                        }
                      ]
                    }
                  ]
                }
              ]
            },
            {
              "partTitle": "PRONUNCIATION",
              "partImage": "",
              "partSubTitle": "Word stress: verbs with two syllables",
              "sets": [
                {
                  "setMarker": "C",
                  "setHeading": null,
                  "setImage": null,
                  "setAudioNumber": null,
                  "audioNumberOrdinal": "",
                  "setAudio": null,
                  "setIgnore": false,
                  "exerciseType": "Speak",
                  "exerciseInstruction": "Listen to the verbs and repeat.",
                  "exercises": [
                    {
                      "sentenceOrdinal": 1,
                      "sentences": [
                        "achieve, arrive, complete"
                      ],
                      "blankedWords": []
                    },
                    {
                      "sentenceOrdinal": 2,
                      "sentences": [
                        "create, regret, study"
                      ],
                      "blankedWords": []
                    }
                  ]
                }
              ]
            }
          ]
        }
      ]
    }
  ]
}